openmlhub/__init__.py
openmlhub/client.py
openmlhub/config.py
openmlhub/importer.py
openmlhub/logger.py
openmlhub/metric.py
openmlhub/model.py
openmlhub-0.2.1.dist-info/METADATA
openmlhub-0.2.1.dist-info/WHEEL
openmlhub-0.2.1.dist-info/licenses/LICENSE
openmlhub-0.2.1.dist-info/RECORD
