Metadata-Version: 2.1
Name: openmlhub
Version: 0.2.1
Summary: A python client for openmlhub repository
Project-URL: Homepage, https://github.com/pegerto/openmlhub-client
Project-URL: Bug Tracker, https://github.com/pegerto/openmlhub-client
Author-email: Pegerto Fernandez <pegerto@gmail.com>
License-File: LICENSE
Classifier: License :: OSI Approved :: GNU General Public License v3 (GPLv3)
Classifier: Operating System :: OS Independent
Classifier: Programming Language :: Python :: 3
Classifier: Topic :: Scientific/Engineering
Classifier: Topic :: Scientific/Engineering :: Artificial Intelligence
Requires-Python: >=3.7
